CONTRIBUTING.md
MANIFEST.in
README.rst
setup.py
docs/HISTORY.txt
docs/LICENSE.GPL
docs/LICENSE.txt
eea/__init__.py
eea.geolocation.egg-info/PKG-INFO
eea.geolocation.egg-info/SOURCES.txt
eea.geolocation.egg-info/dependency_links.txt
eea.geolocation.egg-info/entry_points.txt
eea.geolocation.egg-info/namespace_packages.txt
eea.geolocation.egg-info/not-zip-safe
eea.geolocation.egg-info/requires.txt
eea.geolocation.egg-info/top_level.txt
eea/geolocation/README.txt
eea/geolocation/__init__.py
eea/geolocation/configure.zcml
eea/geolocation/interfaces.py
eea/geolocation/permissions.zcml
eea/geolocation/profiles.zcml
eea/geolocation/setuphandlers.py
eea/geolocation/version.txt
eea/geolocation/browser/__init__.py
eea/geolocation/browser/configure.zcml
eea/geolocation/browser/controlpanel.py
eea/geolocation/browser/edit_taxonomy_data.pt
eea/geolocation/ftests/eea/00_install_addon.js
eea/geolocation/ftests/kgs/00_install_addon.js
eea/geolocation/ftests/plone4/00_install_addon.js
eea/geolocation/ftests/plone5/00_install_addon.js
eea/geolocation/locales/__init__.py
eea/geolocation/locales/eea.pot
eea/geolocation/locales/plone-manual.pot
eea/geolocation/locales/update.sh
eea/geolocation/locales/bg/LC_MESSAGES/eea.po
eea/geolocation/locales/bg/LC_MESSAGES/plone.po
eea/geolocation/locales/cs/LC_MESSAGES/eea.po
eea/geolocation/locales/cs/LC_MESSAGES/plone.po
eea/geolocation/locales/da/LC_MESSAGES/eea.po
eea/geolocation/locales/da/LC_MESSAGES/plone.po
eea/geolocation/locales/de/LC_MESSAGES/eea.po
eea/geolocation/locales/de/LC_MESSAGES/plone.po
eea/geolocation/locales/el/LC_MESSAGES/eea.po
eea/geolocation/locales/el/LC_MESSAGES/plone.po
eea/geolocation/locales/en/LC_MESSAGES/eea.po
eea/geolocation/locales/en/LC_MESSAGES/plone.po
eea/geolocation/locales/es/LC_MESSAGES/eea.po
eea/geolocation/locales/es/LC_MESSAGES/plone.po
eea/geolocation/locales/et/LC_MESSAGES/eea.po
eea/geolocation/locales/et/LC_MESSAGES/plone.po
eea/geolocation/locales/eu/LC_MESSAGES/eea.po
eea/geolocation/locales/eu/LC_MESSAGES/plone.po
eea/geolocation/locales/fi/LC_MESSAGES/eea.po
eea/geolocation/locales/fi/LC_MESSAGES/plone.po
eea/geolocation/locales/fr/LC_MESSAGES/eea.po
eea/geolocation/locales/fr/LC_MESSAGES/plone.po
eea/geolocation/locales/hr/LC_MESSAGES/eea.po
eea/geolocation/locales/hr/LC_MESSAGES/plone.po
